microdados/__init__.py
microdados-0.0.2.dist-info/METADATA
microdados-0.0.2.dist-info/WHEEL
microdados-0.0.2.dist-info/top_level.txt
microdados-0.0.2.dist-info/RECORD
