Metadata-Version: 2.1
Name: microdados
Version: 0.0.2
Summary: A Python library designed to simplify the acquisition and analysis of public microdata
Home-page: UNKNOWN
Author: Cleomar Felipe Rabelo Antoszczyszyn
Author-email: cleomarfelipe@gmail.com
License: UNKNOWN
Platform: UNKNOWN
Requires-Python: >=3.7
